videomap/__init__.py
videomap/cli.py
videomap/streams.py
videomap/videomap.py
videomap-0.1.0.dist-info/DESCRIPTION.rst
videomap-0.1.0.dist-info/METADATA
videomap-0.1.0.dist-info/RECORD
videomap-0.1.0.dist-info/WHEEL
videomap-0.1.0.dist-info/entry_points.txt
videomap-0.1.0.dist-info/metadata.json
videomap-0.1.0.dist-info/top_level.txt
